oboe/__init__.py
oboe_ai-0.1.0.dist-info/METADATA
oboe_ai-0.1.0.dist-info/WHEEL
oboe_ai-0.1.0.dist-info/RECORD
