Metadata-Version: 2.1
Name: oboe-ai
Version: 0.1.0
Summary: Unifying silicon engineering teams and democratizing emulation
License: MIT
Author: Jonathan Terry
Author-email: jonathan.terry@oboecad.com
Requires-Python: >=3.11,<4.0
Classifier: License :: OSI Approved :: MIT License
Classifier: Programming Language :: Python :: 3
Classifier: Programming Language :: Python :: 3.11
Classifier: Programming Language :: Python :: 3.12
Classifier: Programming Language :: Python :: 3.13
